{
  "_id": "fa351368a88131e2",
  "flags": {
    "foundry-ironsworn": {
      "dfid": "Ironsworn/Oracles/Moves/Endure_Stress",
      "category": "Ironsworn/Moves/Suffer",
      "dsid": "move.oracle_rollable:classic/suffer/endure_stress.endure_stress"
    }
  },
  "name": "Endure Stress",
  "description": "",
  "formula": "1d100",
  "replacement": true,
  "displayRoll": true,
  "results": [
    {
      "range": [
        1,
        10
      ],
      "text": "You are overwhelmed. @Compendium[foundry-ironsworn.ironswornmoves.1f978f9faa43d5c6]{Face Desolation}.",
      "_key": "!tables.results!fa351368a88131e2.13947328e745b0a0",
      "_id": "13947328e745b0a0"
    },
    {
      "range": [
        11,
        25
      ],
      "text": "You give up. @Compendium[foundry-ironsworn.ironswornmoves.f968f5e0a837a83a]{Forsake Your Vow} (if possible, one relevant to your current crisis).",
      "_key": "!tables.results!fa351368a88131e2.56d5750563472c75",
      "_id": "56d5750563472c75"
    },
    {
      "range": [
        26,
        50
      ],
      "text": "You give in to a fear or compulsion, and act against your better instincts.",
      "_key": "!tables.results!fa351368a88131e2.3b491c70e69fff6d",
      "_id": "3b491c70e69fff6d"
    },
    {
      "range": [
        51,
        100
      ],
      "text": "You persevere.",
      "_key": "!tables.results!fa351368a88131e2.29f3fd8fa094cb86",
      "_id": "29f3fd8fa094cb86"
    }
  ],
  "folder": "88ca8e80b03ed3dd",
  "sort": 0,
  "img": "icons/dice/d10black.svg",
  "_key": "!tables!fa351368a88131e2"
}