{
  "_id": "32c14ce244acc7a0",
  "type": "progress",
  "name": "Flowering Puppet Vine",
  "img": "icons/magic/nature/plant-vines-skull-green.webp",
  "system": {
    "description": "<div class=\"boxgroup flexrow boxrow\" style=\"margin-bottom: 0.5rem;\">\n  <div class=\"flexcol box\" style=\"justify-content: flex-start;\">\n    <h4 class=\"nogrow\" style=\"margin: 0.5em;\">Features</h4>\n    <p class=\"nogrow\">Writhing tendrils sprouting from a desiccated host</p>\n    <p class=\"nogrow\">Barbed thorns dripping with ichor</p>\n  </div>\n  <div class=\"flexcol box\" style=\"justify-content: flex-start;\">\n    <h4 class=\"nogrow\" style=\"margin: 0.5em;\">Drives</h4>\n    <p class=\"nogrow\">Seek out new hosts</p>\n    <p class=\"nogrow\">Grow and consume</p>\n  </div>\n  <div class=\"flexcol box\" style=\"justify-content: flex-start;\">\n    <h4 class=\"nogrow\" style=\"margin: 0.5em;\">Tactics</h4>\n    <p class=\"nogrow\">Entangle with thorny vines</p>\n    <p class=\"nogrow\">Implant seeds</p>\n    <p class=\"nogrow\">Seize control of a host&#x27;s body</p>\n  </div>\n</div>\n\n<p>After a host is reduced to decaying, mummified flesh and cracked bones, the puppet vine remains anchored to the now-immobile corpse. In this final stage of its life-cycle, the vines sprout alluring crimson flowers to attract unwary victims.</p>\n\n<blockquote>Quest Starter: <p>At a remote settlement, a settler is attacked by a puppet vine and infected. The outpost's fast-thinking healer puts the victim in stasis, stopping—for now—the sprouting and spread of the vines. But time is of the essence. They need someone to transport the stasis pod and its unfortunate occupant to a distant facility for treatment, and your ship is the only one currently planetside. What do they offer to gain your help in this risky mission?</p></blockquote>",
    "rank": 3,
    "current": 0,
    "completed": false,
    "subtype": "progress",
    "starred": false,
    "hasTrack": true,
    "hasClock": false,
    "clockTicks": 0,
    "clockMax": 4
  },
  "effects": [],
  "folder": null,
  "sort": 0,
  "ownership": {
    "default": 0,
    "oPggPZM6rWjfN0q2": 3
  },
  "flags": {},
  "_stats": {
    "systemId": "foundry-ironsworn",
    "systemVersion": "1.22.4",
    "coreVersion": "11.309",
    "createdTime": 1695949021144,
    "modifiedTime": 1695949021144,
    "lastModifiedBy": "oPggPZM6rWjfN0q2"
  },
  "_key": "!items!32c14ce244acc7a0"
}
