{
  "_id": "17e0658e24e16cba",
  "flags": {
    "foundry-ironsworn": {
      "dfid": "Starforged/Oracles/Planets/Ice/Life",
      "category": "Starforged/Oracles/Planets/Ice",
      "dsid": "oracle_rollable:starforged/planet/ice/life"
    }
  },
  "name": "Life",
  "description": "",
  "formula": "1d100",
  "replacement": true,
  "displayRoll": true,
  "results": [
    {
      "range": [
        1,
        20
      ],
      "text": "None",
      "_key": "!tables.results!17e0658e24e16cba.c9a807a9f61a72d1",
      "_id": "c9a807a9f61a72d1"
    },
    {
      "range": [
        21,
        40
      ],
      "text": "Extinct",
      "_key": "!tables.results!17e0658e24e16cba.b258f83e7ef4200d",
      "_id": "b258f83e7ef4200d"
    },
    {
      "range": [
        41,
        70
      ],
      "text": "Scarce",
      "_key": "!tables.results!17e0658e24e16cba.6aa0b676417ae05a",
      "_id": "6aa0b676417ae05a"
    },
    {
      "range": [
        71,
        90
      ],
      "text": "Diverse",
      "_key": "!tables.results!17e0658e24e16cba.1f6f5139d0153d3e",
      "_id": "1f6f5139d0153d3e"
    },
    {
      "range": [
        91,
        97
      ],
      "text": "Bountiful",
      "_key": "!tables.results!17e0658e24e16cba.e445328aad3a6faa",
      "_id": "e445328aad3a6faa"
    },
    {
      "range": [
        98,
        100
      ],
      "text": "Overrun",
      "_key": "!tables.results!17e0658e24e16cba.58144197d9d220be",
      "_id": "58144197d9d220be"
    }
  ],
  "folder": "402fa1e3f9e7707c",
  "sort": 311,
  "img": "icons/dice/d10black.svg",
  "_key": "!tables!17e0658e24e16cba"
}