{
  "_id": "306501658d12dbad",
  "flags": {
    "foundry-ironsworn": {
      "dfid": "Starforged/Oracles/Space/Sector_Name/Prefix",
      "category": "Starforged/Oracles/Space/Sector_Name",
      "dsid": "oracle_rollable:starforged/space/sector_name/prefix"
    }
  },
  "name": "Prefix",
  "description": "",
  "formula": "1d100",
  "replacement": true,
  "displayRoll": true,
  "results": [
    {
      "range": [
        1,
        2
      ],
      "text": "Accursed",
      "_key": "!tables.results!306501658d12dbad.7d8025877802b939",
      "_id": "7d8025877802b939"
    },
    {
      "range": [
        3,
        4
      ],
      "text": "Ashen",
      "_key": "!tables.results!306501658d12dbad.3424460ad65df3c0",
      "_id": "3424460ad65df3c0"
    },
    {
      "range": [
        5,
        6
      ],
      "text": "Asteria",
      "_key": "!tables.results!306501658d12dbad.07b53989b0fb2d75",
      "_id": "07b53989b0fb2d75"
    },
    {
      "range": [
        7,
        8
      ],
      "text": "Bitter",
      "_key": "!tables.results!306501658d12dbad.214bf2bf525673e2",
      "_id": "214bf2bf525673e2"
    },
    {
      "range": [
        9,
        10
      ],
      "text": "Blighted",
      "_key": "!tables.results!306501658d12dbad.7e2776f0d6253fc6",
      "_id": "7e2776f0d6253fc6"
    },
    {
      "range": [
        11,
        12
      ],
      "text": "Bloodied",
      "_key": "!tables.results!306501658d12dbad.a68d3f6be06c26a8",
      "_id": "a68d3f6be06c26a8"
    },
    {
      "range": [
        13,
        14
      ],
      "text": "Boundless",
      "_key": "!tables.results!306501658d12dbad.830bb916c8ee34b4",
      "_id": "830bb916c8ee34b4"
    },
    {
      "range": [
        15,
        16
      ],
      "text": "Burning",
      "_key": "!tables.results!306501658d12dbad.c429929158e5ce7e",
      "_id": "c429929158e5ce7e"
    },
    {
      "range": [
        17,
        18
      ],
      "text": "Cortana",
      "_key": "!tables.results!306501658d12dbad.065064c692733c2f",
      "_id": "065064c692733c2f"
    },
    {
      "range": [
        19,
        20
      ],
      "text": "Corvus",
      "_key": "!tables.results!306501658d12dbad.dcb12c9b10b697d9",
      "_id": "dcb12c9b10b697d9"
    },
    {
      "range": [
        21,
        22
      ],
      "text": "Crimson",
      "_key": "!tables.results!306501658d12dbad.95a409121ac1f187",
      "_id": "95a409121ac1f187"
    },
    {
      "range": [
        23,
        24
      ],
      "text": "Cygnus",
      "_key": "!tables.results!306501658d12dbad.1b19dc15e9946676",
      "_id": "1b19dc15e9946676"
    },
    {
      "range": [
        25,
        26
      ],
      "text": "Delphi",
      "_key": "!tables.results!306501658d12dbad.c25e29c77fcbfa92",
      "_id": "c25e29c77fcbfa92"
    },
    {
      "range": [
        27,
        28
      ],
      "text": "Delphian",
      "_key": "!tables.results!306501658d12dbad.4891ded6ffa7f2d1",
      "_id": "4891ded6ffa7f2d1"
    },
    {
      "range": [
        29,
        30
      ],
      "text": "Devil's",
      "_key": "!tables.results!306501658d12dbad.744e355cd2293266",
      "_id": "744e355cd2293266"
    },
    {
      "range": [
        31,
        32
      ],
      "text": "Ebon",
      "_key": "!tables.results!306501658d12dbad.13e7f34c69fa98df",
      "_id": "13e7f34c69fa98df"
    },
    {
      "range": [
        33,
        34
      ],
      "text": "Essus",
      "_key": "!tables.results!306501658d12dbad.1304d190eda0d92c",
      "_id": "1304d190eda0d92c"
    },
    {
      "range": [
        35,
        36
      ],
      "text": "Fallen",
      "_key": "!tables.results!306501658d12dbad.890bf96b18cea776",
      "_id": "890bf96b18cea776"
    },
    {
      "range": [
        37,
        38
      ],
      "text": "Ferrous",
      "_key": "!tables.results!306501658d12dbad.76478b71e3896de5",
      "_id": "76478b71e3896de5"
    },
    {
      "range": [
        39,
        40
      ],
      "text": "Fool's",
      "_key": "!tables.results!306501658d12dbad.fdff81d8dea970f6",
      "_id": "fdff81d8dea970f6"
    },
    {
      "range": [
        41,
        42
      ],
      "text": "Forgotten",
      "_key": "!tables.results!306501658d12dbad.dbe7a30a7068ec10",
      "_id": "dbe7a30a7068ec10"
    },
    {
      "range": [
        43,
        44
      ],
      "text": "Haunted",
      "_key": "!tables.results!306501658d12dbad.b0c448e49146cbf0",
      "_id": "b0c448e49146cbf0"
    },
    {
      "range": [
        45,
        46
      ],
      "text": "Hidden",
      "_key": "!tables.results!306501658d12dbad.472dd5bc4907882c",
      "_id": "472dd5bc4907882c"
    },
    {
      "range": [
        47,
        48
      ],
      "text": "Hollow",
      "_key": "!tables.results!306501658d12dbad.658fcdb398e4a2de",
      "_id": "658fcdb398e4a2de"
    },
    {
      "range": [
        49,
        50
      ],
      "text": "Igneous",
      "_key": "!tables.results!306501658d12dbad.f225cdedda645cd0",
      "_id": "f225cdedda645cd0"
    },
    {
      "range": [
        51,
        52
      ],
      "text": "Infernal",
      "_key": "!tables.results!306501658d12dbad.746d4475ef6aba48",
      "_id": "746d4475ef6aba48"
    },
    {
      "range": [
        53,
        54
      ],
      "text": "Invidia",
      "_key": "!tables.results!306501658d12dbad.d891f6394d24d48e",
      "_id": "d891f6394d24d48e"
    },
    {
      "range": [
        55,
        56
      ],
      "text": "Iron",
      "_key": "!tables.results!306501658d12dbad.dd948cf1079695d9",
      "_id": "dd948cf1079695d9"
    },
    {
      "range": [
        57,
        58
      ],
      "text": "Kalidas",
      "_key": "!tables.results!306501658d12dbad.c1afaabc77ef5d85",
      "_id": "c1afaabc77ef5d85"
    },
    {
      "range": [
        59,
        60
      ],
      "text": "Kronos",
      "_key": "!tables.results!306501658d12dbad.a8e212def5b57cc0",
      "_id": "a8e212def5b57cc0"
    },
    {
      "range": [
        61,
        62
      ],
      "text": "Lacuna",
      "_key": "!tables.results!306501658d12dbad.2b100f72e156f168",
      "_id": "2b100f72e156f168"
    },
    {
      "range": [
        63,
        64
      ],
      "text": "Lumen",
      "_key": "!tables.results!306501658d12dbad.851850629a511247",
      "_id": "851850629a511247"
    },
    {
      "range": [
        65,
        66
      ],
      "text": "Mobius",
      "_key": "!tables.results!306501658d12dbad.3835c208dd926968",
      "_id": "3835c208dd926968"
    },
    {
      "range": [
        67,
        68
      ],
      "text": "Morien",
      "_key": "!tables.results!306501658d12dbad.46317e7bf4b945c8",
      "_id": "46317e7bf4b945c8"
    },
    {
      "range": [
        69,
        70
      ],
      "text": "Onyx",
      "_key": "!tables.results!306501658d12dbad.3c08e04bba7e0497",
      "_id": "3c08e04bba7e0497"
    },
    {
      "range": [
        71,
        72
      ],
      "text": "Outer",
      "_key": "!tables.results!306501658d12dbad.5ae01fbf8bf64dc2",
      "_id": "5ae01fbf8bf64dc2"
    },
    {
      "range": [
        73,
        74
      ],
      "text": "Sanguis",
      "_key": "!tables.results!306501658d12dbad.fbc42b0ef1c18787",
      "_id": "fbc42b0ef1c18787"
    },
    {
      "range": [
        75,
        76
      ],
      "text": "Scarred",
      "_key": "!tables.results!306501658d12dbad.b5bead8618807697",
      "_id": "b5bead8618807697"
    },
    {
      "range": [
        77,
        78
      ],
      "text": "Scorched",
      "_key": "!tables.results!306501658d12dbad.603f7e299c47b443",
      "_id": "603f7e299c47b443"
    },
    {
      "range": [
        79,
        80
      ],
      "text": "Shattered",
      "_key": "!tables.results!306501658d12dbad.180bd7af2593707d",
      "_id": "180bd7af2593707d"
    },
    {
      "range": [
        81,
        82
      ],
      "text": "Shrouded",
      "_key": "!tables.results!306501658d12dbad.aa0d57545b361a7e",
      "_id": "aa0d57545b361a7e"
    },
    {
      "range": [
        83,
        84
      ],
      "text": "Sindri",
      "_key": "!tables.results!306501658d12dbad.9c675314d214b2ac",
      "_id": "9c675314d214b2ac"
    },
    {
      "range": [
        85,
        86
      ],
      "text": "Solana",
      "_key": "!tables.results!306501658d12dbad.18e93fbbd097a079",
      "_id": "18e93fbbd097a079"
    },
    {
      "range": [
        87,
        88
      ],
      "text": "Stygian",
      "_key": "!tables.results!306501658d12dbad.ded25f60d7e3b1fa",
      "_id": "ded25f60d7e3b1fa"
    },
    {
      "range": [
        89,
        90
      ],
      "text": "Sulaco",
      "_key": "!tables.results!306501658d12dbad.5a93dce5bad08065",
      "_id": "5a93dce5bad08065"
    },
    {
      "range": [
        91,
        92
      ],
      "text": "Sundered",
      "_key": "!tables.results!306501658d12dbad.788ab63c4b374da5",
      "_id": "788ab63c4b374da5"
    },
    {
      "range": [
        93,
        94
      ],
      "text": "Thunor",
      "_key": "!tables.results!306501658d12dbad.343ddf8164111f8b",
      "_id": "343ddf8164111f8b"
    },
    {
      "range": [
        95,
        96
      ],
      "text": "Vanguard",
      "_key": "!tables.results!306501658d12dbad.9b4c9676426eca4f",
      "_id": "9b4c9676426eca4f"
    },
    {
      "range": [
        97,
        98
      ],
      "text": "Veiled",
      "_key": "!tables.results!306501658d12dbad.0f824760878ed1fb",
      "_id": "0f824760878ed1fb"
    },
    {
      "range": [
        99,
        100
      ],
      "text": "Wasted",
      "_key": "!tables.results!306501658d12dbad.56a2b735bd7661b7",
      "_id": "56a2b735bd7661b7"
    }
  ],
  "folder": "158580c8f9018e58",
  "sort": 0,
  "img": "icons/dice/d10black.svg",
  "_key": "!tables!306501658d12dbad"
}